Aryan_STT/__init__.py
Aryan_STT-0.1.dist-info/METADATA
Aryan_STT-0.1.dist-info/WHEEL
Aryan_STT-0.1.dist-info/top_level.txt
Aryan_STT-0.1.dist-info/RECORD
