Metadata-Version: 2.1
Name: Aryan-STT
Version: 0.1
Summary: this is speech to text package created by Aryan Sahani
Author: Aryan Sahani
Author-email: sahaniaryan321@gmail.com
